awkward/__init__.py
awkward/numba/__init__.py
awkward/numba/array/__init__.py
awkward/numba/array/base.py
awkward/numba/array/chunked.py
awkward/numba/array/indexed.py
awkward/numba/array/jagged.py
awkward/numba/array/masked.py
awkward/numba/array/objects.py
awkward/numba/array/table.py
awkward/numba/array/union.py
awkward/numba/array/virtual.py
awkward_numba-0.14.0.dist-info/METADATA
awkward_numba-0.14.0.dist-info/WHEEL
awkward_numba-0.14.0.dist-info/top_level.txt
awkward_numba-0.14.0.dist-info/RECORD
